validate_bes_xml/__init__.py
validate_bes_xml/__main__.py
validate_bes_xml/validate_bes_xml.py
validate_bes_xml/schemas/BES.xsd
validate_bes_xml/schemas/BESAPI.xsd
validate_bes_xml/schemas/BESDomain.xsd
validate_bes_xml/schemas/BESOJO.xsd
validate_bes_xml-1.1.2.dist-info/LICENSE
validate_bes_xml-1.1.2.dist-info/METADATA
validate_bes_xml-1.1.2.dist-info/WHEEL
validate_bes_xml-1.1.2.dist-info/top_level.txt
validate_bes_xml-1.1.2.dist-info/RECORD
