Metadata-Version: 2.1
Name: validate-bes-xml
Version: 1.1.2
Summary: A python bes xml validator
Home-page: https://github.com/jgstew/validate_bes_xml
Author: JGStew
Author-email: noreply@jgstew.com
License: UNKNOWN
Project-URL: Bug Tracker, https://github.com/jgstew/validate_bes_xml/issues
Platform: UNKNOWN
Classifier: Programming Language :: Python :: 3
Classifier: License :: OSI Approved :: MIT License
Classifier: Operating System :: OS Independent
Requires-Python: >=3.5
License-File: LICENSE
Requires-Dist: lxml
